django_namespaced-1.0.1.dist-info/DESCRIPTION.rst
django_namespaced-1.0.1.dist-info/METADATA
django_namespaced-1.0.1.dist-info/metadata.json
django_namespaced-1.0.1.dist-info/RECORD
django_namespaced-1.0.1.dist-info/top_level.txt
django_namespaced-1.0.1.dist-info/WHEEL
namespaced/__init__.py
namespaced/_version.py
namespaced/context_processors.py
